{
    "name": "R-F2-W2-100",
    "nodes": {
        "depot": [
            {
                "id": 0,
                "x": 14.12,
                "y": 15.53,
                "r": "start",
                "e": 0,
                "s": 0,
                "l": 600
            },
            {
                "id": 201,
                "x": 14.12,
                "y": 15.53,
                "r": "end",
                "e": 0,
                "s": 0,
                "l": 600
            }
        ],
        "pickup": [
            {
                "id": 1,
                "x": 30.37,
                "y": 56.16,
                "r": "(+,f20')",
                "e": 186,
                "s": 30,
                "l": 306,
                "delivery": 101
            },
            {
                "id": 2,
                "x": 6.18,
                "y": 45.3,
                "r": "(+,f20')",
                "e": 258,
                "s": 30,
                "l": 378,
                "delivery": 102
            },
            {
                "id": 3,
                "x": 17.39,
                "y": 57.54,
                "r": "(+,e20')",
                "e": 229,
                "s": 30,
                "l": 349,
                "delivery": 103
            },
            {
                "id": 4,
                "x": 47.68,
                "y": 32.61,
                "r": "(+,e20')",
                "e": 193,
                "s": 30,
                "l": 313,
                "delivery": 104
            },
            {
                "id": 5,
                "x": 43.54,
                "y": 1.44,
                "r": "(+,e20')",
                "e": 57,
                "s": 30,
                "l": 177,
                "delivery": 105
            },
            {
                "id": 6,
                "x": 41.63,
                "y": 9.58,
                "r": "(+,f20')",
                "e": 31,
                "s": 30,
                "l": 151,
                "delivery": 106
            },
            {
                "id": 7,
                "x": 47.02,
                "y": 47.37,
                "r": "(+,f20')",
                "e": 261,
                "s": 30,
                "l": 381,
                "delivery": 107
            },
            {
                "id": 8,
                "x": 32.61,
                "y": 0.64,
                "r": "(+,f20')",
                "e": 75,
                "s": 30,
                "l": 195,
                "delivery": 108
            },
            {
                "id": 9,
                "x": 55.19,
                "y": 54.22,
                "r": "(+,e20')",
                "e": 338,
                "s": 30,
                "l": 458,
                "delivery": 109
            },
            {
                "id": 10,
                "x": 16.64,
                "y": 48.59,
                "r": "(+,f20')",
                "e": 288,
                "s": 30,
                "l": 408,
                "delivery": 110
            },
            {
                "id": 11,
                "x": 16.56,
                "y": 25.38,
                "r": "(+,f20')",
                "e": 18,
                "s": 30,
                "l": 138,
                "delivery": 111
            },
            {
                "id": 12,
                "x": 43.36,
                "y": 37.75,
                "r": "(+,e20')",
                "e": 242,
                "s": 30,
                "l": 362,
                "delivery": 112
            },
            {
                "id": 13,
                "x": 37.98,
                "y": 0.36,
                "r": "(+,f20')",
                "e": 351,
                "s": 30,
                "l": 471,
                "delivery": 113
            },
            {
                "id": 14,
                "x": 25.49,
                "y": 1.31,
                "r": "(+,f20')",
                "e": 337,
                "s": 30,
                "l": 457,
                "delivery": 114
            },
            {
                "id": 15,
                "x": 43.5,
                "y": 46.64,
                "r": "(+,f20')",
                "e": 219,
                "s": 30,
                "l": 339,
                "delivery": 115
            },
            {
                "id": 16,
                "x": 22.15,
                "y": 24.21,
                "r": "(+,f20')",
                "e": 117,
                "s": 30,
                "l": 237,
                "delivery": 116
            },
            {
                "id": 17,
                "x": 14.02,
                "y": 29.09,
                "r": "(+,e20')",
                "e": 15,
                "s": 30,
                "l": 135,
                "delivery": 117
            },
            {
                "id": 18,
                "x": 40.89,
                "y": 11.63,
                "r": "(+,e20')",
                "e": 279,
                "s": 30,
                "l": 399,
                "delivery": 118
            },
            {
                "id": 19,
                "x": 33.39,
                "y": 57.17,
                "r": "(+,f20')",
                "e": 110,
                "s": 30,
                "l": 230,
                "delivery": 119
            },
            {
                "id": 20,
                "x": 18.9,
                "y": 5.78,
                "r": "(+,f20')",
                "e": 281,
                "s": 30,
                "l": 401,
                "delivery": 120
            },
            {
                "id": 21,
                "x": 55.76,
                "y": 42.08,
                "r": "(+,e20')",
                "e": 197,
                "s": 30,
                "l": 317,
                "delivery": 121
            },
            {
                "id": 22,
                "x": 9.99,
                "y": 4.33,
                "r": "(+,f20')",
                "e": 186,
                "s": 30,
                "l": 306,
                "delivery": 122
            },
            {
                "id": 23,
                "x": 49.77,
                "y": 15.87,
                "r": "(+,f20')",
                "e": 143,
                "s": 30,
                "l": 263,
                "delivery": 123
            },
            {
                "id": 24,
                "x": 36.97,
                "y": 35.67,
                "r": "(+,f20')",
                "e": 92,
                "s": 30,
                "l": 212,
                "delivery": 124
            },
            {
                "id": 25,
                "x": 42.37,
                "y": 42.25,
                "r": "(+,f20')",
                "e": 146,
                "s": 30,
                "l": 266,
                "delivery": 125
            },
            {
                "id": 26,
                "x": 22.23,
                "y": 33.12,
                "r": "(+,f20')",
                "e": 227,
                "s": 30,
                "l": 347,
                "delivery": 126
            },
            {
                "id": 27,
                "x": 33.98,
                "y": 44.42,
                "r": "(+,f20')",
                "e": 169,
                "s": 30,
                "l": 289,
                "delivery": 127
            },
            {
                "id": 28,
                "x": 17.92,
                "y": 53.02,
                "r": "(+,f20')",
                "e": 379,
                "s": 30,
                "l": 499,
                "delivery": 128
            },
            {
                "id": 29,
                "x": 12.56,
                "y": 21.76,
                "r": "(+,f20')",
                "e": 21,
                "s": 30,
                "l": 141,
                "delivery": 129
            },
            {
                "id": 30,
                "x": 36.41,
                "y": 10.99,
                "r": "(+,e20')",
                "e": 80,
                "s": 30,
                "l": 200,
                "delivery": 130
            },
            {
                "id": 31,
                "x": 11.88,
                "y": 22.1,
                "r": "(+,f20')",
                "e": 360,
                "s": 30,
                "l": 480,
                "delivery": 131
            },
            {
                "id": 32,
                "x": 17.84,
                "y": 6.78,
                "r": "(+,f20')",
                "e": 115,
                "s": 30,
                "l": 235,
                "delivery": 132
            },
            {
                "id": 33,
                "x": 54.67,
                "y": 54.85,
                "r": "(+,e20')",
                "e": 255,
                "s": 30,
                "l": 375,
                "delivery": 133
            },
            {
                "id": 34,
                "x": 51.1,
                "y": 23.09,
                "r": "(+,e20')",
                "e": 55,
                "s": 30,
                "l": 175,
                "delivery": 134
            },
            {
                "id": 35,
                "x": 34.76,
                "y": 14.31,
                "r": "(+,e20')",
                "e": 74,
                "s": 30,
                "l": 194,
                "delivery": 135
            },
            {
                "id": 36,
                "x": 52.6,
                "y": 29.44,
                "r": "(+,e20')",
                "e": 217,
                "s": 30,
                "l": 337,
                "delivery": 136
            },
            {
                "id": 37,
                "x": 21.9,
                "y": 40.91,
                "r": "(+,e20')",
                "e": 159,
                "s": 30,
                "l": 279,
                "delivery": 137
            },
            {
                "id": 38,
                "x": 25.65,
                "y": 15.49,
                "r": "(+,e20')",
                "e": 312,
                "s": 30,
                "l": 432,
                "delivery": 138
            },
            {
                "id": 39,
                "x": 22.31,
                "y": 6.64,
                "r": "(+,f20')",
                "e": 105,
                "s": 30,
                "l": 225,
                "delivery": 139
            },
            {
                "id": 40,
                "x": 59.26,
                "y": 16.23,
                "r": "(+,f20')",
                "e": 64,
                "s": 30,
                "l": 184,
                "delivery": 140
            },
            {
                "id": 41,
                "x": 45.66,
                "y": 32.25,
                "r": "(+,f20')",
                "e": 58,
                "s": 30,
                "l": 178,
                "delivery": 141
            },
            {
                "id": 42,
                "x": 56.75,
                "y": 42.94,
                "r": "(+,e20')",
                "e": 181,
                "s": 30,
                "l": 301,
                "delivery": 142
            },
            {
                "id": 43,
                "x": 33.79,
                "y": 52.94,
                "r": "(+,f20')",
                "e": 291,
                "s": 30,
                "l": 411,
                "delivery": 143
            },
            {
                "id": 44,
                "x": 29.52,
                "y": 59.25,
                "r": "(+,e20')",
                "e": 121,
                "s": 30,
                "l": 241,
                "delivery": 144
            },
            {
                "id": 45,
                "x": 22.9,
                "y": 20.3,
                "r": "(+,f20')",
                "e": 197,
                "s": 30,
                "l": 317,
                "delivery": 145
            },
            {
                "id": 46,
                "x": 51.2,
                "y": 26.52,
                "r": "(+,f20')",
                "e": 253,
                "s": 30,
                "l": 373,
                "delivery": 146
            },
            {
                "id": 47,
                "x": 41.3,
                "y": 35.88,
                "r": "(+,e20')",
                "e": 310,
                "s": 30,
                "l": 430,
                "delivery": 147
            },
            {
                "id": 48,
                "x": 56.28,
                "y": 18.36,
                "r": "(+,f20')",
                "e": 200,
                "s": 30,
                "l": 320,
                "delivery": 148
            },
            {
                "id": 49,
                "x": 39.81,
                "y": 51.22,
                "r": "(+,e20')",
                "e": 292,
                "s": 30,
                "l": 412,
                "delivery": 149
            },
            {
                "id": 50,
                "x": 41.24,
                "y": 39.7,
                "r": "(+,f20')",
                "e": 80,
                "s": 30,
                "l": 200,
                "delivery": 150
            },
            {
                "id": 51,
                "x": 54.83,
                "y": 7.11,
                "r": "(+,e20')",
                "e": 177,
                "s": 30,
                "l": 297,
                "delivery": 151
            },
            {
                "id": 52,
                "x": 46.45,
                "y": 13.78,
                "r": "(+,f20')",
                "e": 79,
                "s": 30,
                "l": 199,
                "delivery": 152
            },
            {
                "id": 53,
                "x": 0.57,
                "y": 13.03,
                "r": "(+,f20')",
                "e": 218,
                "s": 30,
                "l": 338,
                "delivery": 153
            },
            {
                "id": 54,
                "x": 36.39,
                "y": 58.88,
                "r": "(+,f20')",
                "e": 172,
                "s": 30,
                "l": 292,
                "delivery": 154
            },
            {
                "id": 55,
                "x": 30.23,
                "y": 33.78,
                "r": "(+,f20')",
                "e": 58,
                "s": 30,
                "l": 178,
                "delivery": 155
            },
            {
                "id": 56,
                "x": 2.49,
                "y": 44.6,
                "r": "(+,f20')",
                "e": 306,
                "s": 30,
                "l": 426,
                "delivery": 156
            },
            {
                "id": 57,
                "x": 4.87,
                "y": 27.18,
                "r": "(+,e20')",
                "e": 160,
                "s": 30,
                "l": 280,
                "delivery": 157
            },
            {
                "id": 58,
                "x": 2.04,
                "y": 35.66,
                "r": "(+,f20')",
                "e": 180,
                "s": 30,
                "l": 300,
                "delivery": 158
            },
            {
                "id": 59,
                "x": 12.77,
                "y": 1.09,
                "r": "(+,f20')",
                "e": 293,
                "s": 30,
                "l": 413,
                "delivery": 159
            },
            {
                "id": 60,
                "x": 29.15,
                "y": 34.5,
                "r": "(+,f20')",
                "e": 97,
                "s": 30,
                "l": 217,
                "delivery": 160
            },
            {
                "id": 61,
                "x": 43.77,
                "y": 49.57,
                "r": "(+,e20')",
                "e": 335,
                "s": 30,
                "l": 455,
                "delivery": 161
            },
            {
                "id": 62,
                "x": 25.71,
                "y": 23.19,
                "r": "(+,f20')",
                "e": 278,
                "s": 30,
                "l": 398,
                "delivery": 162
            },
            {
                "id": 63,
                "x": 24.81,
                "y": 33.39,
                "r": "(+,f20')",
                "e": 228,
                "s": 30,
                "l": 348,
                "delivery": 163
            },
            {
                "id": 64,
                "x": 53.69,
                "y": 9.26,
                "r": "(+,f20')",
                "e": 213,
                "s": 30,
                "l": 333,
                "delivery": 164
            },
            {
                "id": 65,
                "x": 13.8,
                "y": 33.37,
                "r": "(+,e20')",
                "e": 286,
                "s": 30,
                "l": 406,
                "delivery": 165
            },
            {
                "id": 66,
                "x": 16.13,
                "y": 26.78,
                "r": "(+,e20')",
                "e": 358,
                "s": 30,
                "l": 478,
                "delivery": 166
            },
            {
                "id": 67,
                "x": 16.69,
                "y": 48.83,
                "r": "(+,f20')",
                "e": 253,
                "s": 30,
                "l": 373,
                "delivery": 167
            },
            {
                "id": 68,
                "x": 56.13,
                "y": 59.69,
                "r": "(+,f20')",
                "e": 168,
                "s": 30,
                "l": 288,
                "delivery": 168
            },
            {
                "id": 69,
                "x": 4.28,
                "y": 55.78,
                "r": "(+,f20')",
                "e": 153,
                "s": 30,
                "l": 273,
                "delivery": 169
            },
            {
                "id": 70,
                "x": 6.05,
                "y": 59.34,
                "r": "(+,f20')",
                "e": 248,
                "s": 30,
                "l": 368,
                "delivery": 170
            },
            {
                "id": 71,
                "x": 48.08,
                "y": 17.66,
                "r": "(+,e20')",
                "e": 198,
                "s": 30,
                "l": 318,
                "delivery": 171
            },
            {
                "id": 72,
                "x": 32.58,
                "y": 42.65,
                "r": "(+,e20')",
                "e": 174,
                "s": 30,
                "l": 294,
                "delivery": 172
            },
            {
                "id": 73,
                "x": 38.24,
                "y": 31.45,
                "r": "(+,e20')",
                "e": 92,
                "s": 30,
                "l": 212,
                "delivery": 173
            },
            {
                "id": 74,
                "x": 41.61,
                "y": 17.43,
                "r": "(+,e20')",
                "e": 241,
                "s": 30,
                "l": 361,
                "delivery": 174
            },
            {
                "id": 75,
                "x": 19.57,
                "y": 14.29,
                "r": "(+,e20')",
                "e": 299,
                "s": 30,
                "l": 419,
                "delivery": 175
            },
            {
                "id": 76,
                "x": 52.53,
                "y": 8.38,
                "r": "(+,e20')",
                "e": 297,
                "s": 30,
                "l": 417,
                "delivery": 176
            },
            {
                "id": 77,
                "x": 58.59,
                "y": 9.63,
                "r": "(+,f20')",
                "e": 352,
                "s": 30,
                "l": 472,
                "delivery": 177
            },
            {
                "id": 78,
                "x": 14.56,
                "y": 11.27,
                "r": "(+,f20')",
                "e": 173,
                "s": 30,
                "l": 293,
                "delivery": 178
            },
            {
                "id": 79,
                "x": 21.91,
                "y": 6.81,
                "r": "(+,e20')",
                "e": 259,
                "s": 30,
                "l": 379,
                "delivery": 179
            },
            {
                "id": 80,
                "x": 53.53,
                "y": 56.09,
                "r": "(+,f20')",
                "e": 174,
                "s": 30,
                "l": 294,
                "delivery": 180
            },
            {
                "id": 81,
                "x": 39.05,
                "y": 29.08,
                "r": "(+,e20')",
                "e": 119,
                "s": 30,
                "l": 239,
                "delivery": 181
            },
            {
                "id": 82,
                "x": 53.52,
                "y": 35.42,
                "r": "(+,f20')",
                "e": 312,
                "s": 30,
                "l": 432,
                "delivery": 182
            },
            {
                "id": 83,
                "x": 26.6,
                "y": 5.59,
                "r": "(+,f20')",
                "e": 267,
                "s": 30,
                "l": 387,
                "delivery": 183
            },
            {
                "id": 84,
                "x": 31.61,
                "y": 2.19,
                "r": "(+,e20')",
                "e": 337,
                "s": 30,
                "l": 457,
                "delivery": 184
            },
            {
                "id": 85,
                "x": 25.19,
                "y": 8.99,
                "r": "(+,e20')",
                "e": 105,
                "s": 30,
                "l": 225,
                "delivery": 185
            },
            {
                "id": 86,
                "x": 22.56,
                "y": 1.34,
                "r": "(+,e20')",
                "e": 20,
                "s": 30,
                "l": 140,
                "delivery": 186
            },
            {
                "id": 87,
                "x": 52.52,
                "y": 21.31,
                "r": "(+,f20')",
                "e": 243,
                "s": 30,
                "l": 363,
                "delivery": 187
            },
            {
                "id": 88,
                "x": 29.91,
                "y": 21.74,
                "r": "(+,e20')",
                "e": 246,
                "s": 30,
                "l": 366,
                "delivery": 188
            },
            {
                "id": 89,
                "x": 27.29,
                "y": 25.43,
                "r": "(+,e20')",
                "e": 218,
                "s": 30,
                "l": 338,
                "delivery": 189
            },
            {
                "id": 90,
                "x": 37.94,
                "y": 51.91,
                "r": "(+,f20')",
                "e": 54,
                "s": 30,
                "l": 174,
                "delivery": 190
            },
            {
                "id": 91,
                "x": 24.67,
                "y": 55.7,
                "r": "(+,e20')",
                "e": 91,
                "s": 30,
                "l": 211,
                "delivery": 191
            },
            {
                "id": 92,
                "x": 45.24,
                "y": 53.42,
                "r": "(+,f20')",
                "e": 201,
                "s": 30,
                "l": 321,
                "delivery": 192
            },
            {
                "id": 93,
                "x": 58.43,
                "y": 27.24,
                "r": "(+,e20')",
                "e": 284,
                "s": 30,
                "l": 404,
                "delivery": 193
            },
            {
                "id": 94,
                "x": 42.46,
                "y": 16.63,
                "r": "(+,e20')",
                "e": 282,
                "s": 30,
                "l": 402,
                "delivery": 194
            },
            {
                "id": 95,
                "x": 51.69,
                "y": 8.69,
                "r": "(+,f20')",
                "e": 47,
                "s": 30,
                "l": 167,
                "delivery": 195
            },
            {
                "id": 96,
                "x": 7.87,
                "y": 17.01,
                "r": "(+,e20')",
                "e": 358,
                "s": 30,
                "l": 478,
                "delivery": 196
            },
            {
                "id": 97,
                "x": 14.86,
                "y": 18.56,
                "r": "(+,e20')",
                "e": 88,
                "s": 30,
                "l": 208,
                "delivery": 197
            },
            {
                "id": 98,
                "x": 36.01,
                "y": 47.54,
                "r": "(+,e20')",
                "e": 211,
                "s": 30,
                "l": 331,
                "delivery": 198
            },
            {
                "id": 99,
                "x": 5.47,
                "y": 46.56,
                "r": "(+,f20')",
                "e": 87,
                "s": 30,
                "l": 207,
                "delivery": 199
            },
            {
                "id": 100,
                "x": 44.64,
                "y": 32.53,
                "r": "(+,e20')",
                "e": 50,
                "s": 30,
                "l": 170,
                "delivery": 200
            }
        ],
        "delivery": [
            {
                "id": 101,
                "x": 51.72,
                "y": 9.18,
                "r": "(-,f20')",
                "e": 379,
                "s": 30,
                "l": 499,
                "pickup": 1
            },
            {
                "id": 102,
                "x": 51.07,
                "y": 17.5,
                "r": "(-,f20')",
                "e": 367,
                "s": 30,
                "l": 487,
                "pickup": 2
            },
            {
                "id": 103,
                "x": 9.87,
                "y": 46.27,
                "r": "(-,e20')",
                "e": 407,
                "s": 30,
                "l": 527,
                "pickup": 3
            },
            {
                "id": 104,
                "x": 0.08,
                "y": 58.11,
                "r": "(-,e20')",
                "e": 376,
                "s": 30,
                "l": 496,
                "pickup": 4
            },
            {
                "id": 105,
                "x": 45.84,
                "y": 33.03,
                "r": "(-,e20')",
                "e": 378,
                "s": 30,
                "l": 498,
                "pickup": 5
            },
            {
                "id": 106,
                "x": 45.7,
                "y": 35.11,
                "r": "(-,f20')",
                "e": 88,
                "s": 30,
                "l": 208,
                "pickup": 6
            },
            {
                "id": 107,
                "x": 25.19,
                "y": 51.09,
                "r": "(-,f20')",
                "e": 385,
                "s": 30,
                "l": 505,
                "pickup": 7
            },
            {
                "id": 108,
                "x": 15.89,
                "y": 50.09,
                "r": "(-,f20')",
                "e": 275,
                "s": 30,
                "l": 395,
                "pickup": 8
            },
            {
                "id": 109,
                "x": 31.42,
                "y": 16.16,
                "r": "(-,e20')",
                "e": 426,
                "s": 30,
                "l": 546,
                "pickup": 9
            },
            {
                "id": 110,
                "x": 35.04,
                "y": 31.4,
                "r": "(-,f20')",
                "e": 369,
                "s": 30,
                "l": 489,
                "pickup": 10
            },
            {
                "id": 111,
                "x": 10.95,
                "y": 26.05,
                "r": "(-,f20')",
                "e": 207,
                "s": 30,
                "l": 327,
                "pickup": 11
            },
            {
                "id": 112,
                "x": 2.54,
                "y": 21.59,
                "r": "(-,e20')",
                "e": 372,
                "s": 30,
                "l": 492,
                "pickup": 12
            },
            {
                "id": 113,
                "x": 34.23,
                "y": 0.94,
                "r": "(-,f20')",
                "e": 421,
                "s": 30,
                "l": 541,
                "pickup": 13
            },
            {
                "id": 114,
                "x": 44.48,
                "y": 23.23,
                "r": "(-,f20')",
                "e": 413,
                "s": 30,
                "l": 533,
                "pickup": 14
            },
            {
                "id": 115,
                "x": 22.52,
                "y": 9.32,
                "r": "(-,f20')",
                "e": 340,
                "s": 30,
                "l": 460,
                "pickup": 15
            },
            {
                "id": 116,
                "x": 35.07,
                "y": 33.38,
                "r": "(-,f20')",
                "e": 395,
                "s": 30,
                "l": 515,
                "pickup": 16
            },
            {
                "id": 117,
                "x": 43.49,
                "y": 57.19,
                "r": "(-,e20')",
                "e": 358,
                "s": 30,
                "l": 478,
                "pickup": 17
            },
            {
                "id": 118,
                "x": 35.38,
                "y": 8.67,
                "r": "(-,e20')",
                "e": 372,
                "s": 30,
                "l": 492,
                "pickup": 18
            },
            {
                "id": 119,
                "x": 6.89,
                "y": 23.48,
                "r": "(-,f20')",
                "e": 391,
                "s": 30,
                "l": 511,
                "pickup": 19
            },
            {
                "id": 120,
                "x": 55.04,
                "y": 49.67,
                "r": "(-,f20')",
                "e": 373,
                "s": 30,
                "l": 493,
                "pickup": 20
            },
            {
                "id": 121,
                "x": 37.13,
                "y": 53.97,
                "r": "(-,e20')",
                "e": 374,
                "s": 30,
                "l": 494,
                "pickup": 21
            },
            {
                "id": 122,
                "x": 11.27,
                "y": 22.19,
                "r": "(-,f20')",
                "e": 323,
                "s": 30,
                "l": 443,
                "pickup": 22
            },
            {
                "id": 123,
                "x": 6.61,
                "y": 3.96,
                "r": "(-,f20')",
                "e": 382,
                "s": 30,
                "l": 502,
                "pickup": 23
            },
            {
                "id": 124,
                "x": 47.09,
                "y": 7.38,
                "r": "(-,f20')",
                "e": 285,
                "s": 30,
                "l": 405,
                "pickup": 24
            },
            {
                "id": 125,
                "x": 36.96,
                "y": 57.68,
                "r": "(-,f20')",
                "e": 221,
                "s": 30,
                "l": 341,
                "pickup": 25
            },
            {
                "id": 126,
                "x": 3.46,
                "y": 17.07,
                "r": "(-,f20')",
                "e": 343,
                "s": 30,
                "l": 463,
                "pickup": 26
            },
            {
                "id": 127,
                "x": 12.13,
                "y": 55.32,
                "r": "(-,f20')",
                "e": 243,
                "s": 30,
                "l": 363,
                "pickup": 27
            },
            {
                "id": 128,
                "x": 10.24,
                "y": 22.19,
                "r": "(-,f20')",
                "e": 441,
                "s": 30,
                "l": 561,
                "pickup": 28
            },
            {
                "id": 129,
                "x": 3.51,
                "y": 6.7,
                "r": "(-,f20')",
                "e": 374,
                "s": 30,
                "l": 494,
                "pickup": 29
            },
            {
                "id": 130,
                "x": 22.33,
                "y": 37.45,
                "r": "(-,e20')",
                "e": 306,
                "s": 30,
                "l": 426,
                "pickup": 30
            },
            {
                "id": 131,
                "x": 30.52,
                "y": 15.79,
                "r": "(-,f20')",
                "e": 412,
                "s": 30,
                "l": 532,
                "pickup": 31
            },
            {
                "id": 132,
                "x": 58.2,
                "y": 17.22,
                "r": "(-,f20')",
                "e": 264,
                "s": 30,
                "l": 384,
                "pickup": 32
            },
            {
                "id": 133,
                "x": 39.81,
                "y": 24.68,
                "r": "(-,e20')",
                "e": 370,
                "s": 30,
                "l": 490,
                "pickup": 33
            },
            {
                "id": 134,
                "x": 9.67,
                "y": 40.01,
                "r": "(-,e20')",
                "e": 143,
                "s": 30,
                "l": 263,
                "pickup": 34
            },
            {
                "id": 135,
                "x": 41.74,
                "y": 15.91,
                "r": "(-,e20')",
                "e": 346,
                "s": 30,
                "l": 466,
                "pickup": 35
            },
            {
                "id": 136,
                "x": 44.23,
                "y": 54.04,
                "r": "(-,e20')",
                "e": 305,
                "s": 30,
                "l": 425,
                "pickup": 36
            },
            {
                "id": 137,
                "x": 11.05,
                "y": 41.16,
                "r": "(-,e20')",
                "e": 228,
                "s": 30,
                "l": 348,
                "pickup": 37
            },
            {
                "id": 138,
                "x": 3.91,
                "y": 36.54,
                "r": "(-,e20')",
                "e": 395,
                "s": 30,
                "l": 515,
                "pickup": 38
            },
            {
                "id": 139,
                "x": 49.99,
                "y": 7.66,
                "r": "(-,f20')",
                "e": 302,
                "s": 30,
                "l": 422,
                "pickup": 39
            },
            {
                "id": 140,
                "x": 38.2,
                "y": 19.44,
                "r": "(-,f20')",
                "e": 202,
                "s": 30,
                "l": 322,
                "pickup": 40
            },
            {
                "id": 141,
                "x": 44.31,
                "y": 49.69,
                "r": "(-,f20')",
                "e": 360,
                "s": 30,
                "l": 480,
                "pickup": 41
            },
            {
                "id": 142,
                "x": 34.44,
                "y": 45.11,
                "r": "(-,e20')",
                "e": 346,
                "s": 30,
                "l": 466,
                "pickup": 42
            },
            {
                "id": 143,
                "x": 11.53,
                "y": 17.2,
                "r": "(-,f20')",
                "e": 378,
                "s": 30,
                "l": 498,
                "pickup": 43
            },
            {
                "id": 144,
                "x": 7.49,
                "y": 57.6,
                "r": "(-,e20')",
                "e": 218,
                "s": 30,
                "l": 338,
                "pickup": 44
            },
            {
                "id": 145,
                "x": 31.13,
                "y": 31.06,
                "r": "(-,f20')",
                "e": 361,
                "s": 30,
                "l": 481,
                "pickup": 45
            },
            {
                "id": 146,
                "x": 23.5,
                "y": 3.55,
                "r": "(-,f20')",
                "e": 396,
                "s": 30,
                "l": 516,
                "pickup": 46
            },
            {
                "id": 147,
                "x": 23.58,
                "y": 31.45,
                "r": "(-,e20')",
                "e": 359,
                "s": 30,
                "l": 479,
                "pickup": 47
            },
            {
                "id": 148,
                "x": 44.77,
                "y": 5.59,
                "r": "(-,f20')",
                "e": 333,
                "s": 30,
                "l": 453,
                "pickup": 48
            },
            {
                "id": 149,
                "x": 8.33,
                "y": 0.66,
                "r": "(-,e20')",
                "e": 405,
                "s": 30,
                "l": 525,
                "pickup": 49
            },
            {
                "id": 150,
                "x": 53.46,
                "y": 9.63,
                "r": "(-,f20')",
                "e": 287,
                "s": 30,
                "l": 407,
                "pickup": 50
            },
            {
                "id": 151,
                "x": 38.32,
                "y": 2.45,
                "r": "(-,e20')",
                "e": 273,
                "s": 30,
                "l": 393,
                "pickup": 51
            },
            {
                "id": 152,
                "x": 24.93,
                "y": 41.77,
                "r": "(-,f20')",
                "e": 327,
                "s": 30,
                "l": 447,
                "pickup": 52
            },
            {
                "id": 153,
                "x": 52.69,
                "y": 36.39,
                "r": "(-,f20')",
                "e": 377,
                "s": 30,
                "l": 497,
                "pickup": 53
            },
            {
                "id": 154,
                "x": 52.67,
                "y": 50.19,
                "r": "(-,f20')",
                "e": 275,
                "s": 30,
                "l": 395,
                "pickup": 54
            },
            {
                "id": 155,
                "x": 5.74,
                "y": 4.48,
                "r": "(-,f20')",
                "e": 171,
                "s": 30,
                "l": 291,
                "pickup": 55
            },
            {
                "id": 156,
                "x": 8.65,
                "y": 33.65,
                "r": "(-,f20')",
                "e": 393,
                "s": 30,
                "l": 513,
                "pickup": 56
            },
            {
                "id": 157,
                "x": 9.74,
                "y": 34.62,
                "r": "(-,e20')",
                "e": 347,
                "s": 30,
                "l": 467,
                "pickup": 57
            },
            {
                "id": 158,
                "x": 24.15,
                "y": 46.56,
                "r": "(-,f20')",
                "e": 339,
                "s": 30,
                "l": 459,
                "pickup": 58
            },
            {
                "id": 159,
                "x": 9.8,
                "y": 25.54,
                "r": "(-,f20')",
                "e": 364,
                "s": 30,
                "l": 484,
                "pickup": 59
            },
            {
                "id": 160,
                "x": 19.54,
                "y": 33.13,
                "r": "(-,f20')",
                "e": 188,
                "s": 30,
                "l": 308,
                "pickup": 60
            },
            {
                "id": 161,
                "x": 50.53,
                "y": 33.43,
                "r": "(-,e20')",
                "e": 387,
                "s": 30,
                "l": 507,
                "pickup": 61
            },
            {
                "id": 162,
                "x": 50.29,
                "y": 39.58,
                "r": "(-,f20')",
                "e": 352,
                "s": 30,
                "l": 472,
                "pickup": 62
            },
            {
                "id": 163,
                "x": 40.87,
                "y": 44.27,
                "r": "(-,f20')",
                "e": 322,
                "s": 30,
                "l": 442,
                "pickup": 63
            },
            {
                "id": 164,
                "x": 8.36,
                "y": 20.64,
                "r": "(-,f20')",
                "e": 303,
                "s": 30,
                "l": 423,
                "pickup": 64
            },
            {
                "id": 165,
                "x": 11.13,
                "y": 53.15,
                "r": "(-,e20')",
                "e": 373,
                "s": 30,
                "l": 493,
                "pickup": 65
            },
            {
                "id": 166,
                "x": 12.38,
                "y": 22.83,
                "r": "(-,e20')",
                "e": 403,
                "s": 30,
                "l": 523,
                "pickup": 66
            },
            {
                "id": 167,
                "x": 58.05,
                "y": 51.87,
                "r": "(-,f20')",
                "e": 384,
                "s": 30,
                "l": 504,
                "pickup": 67
            },
            {
                "id": 168,
                "x": 16.46,
                "y": 34.78,
                "r": "(-,f20')",
                "e": 254,
                "s": 30,
                "l": 374,
                "pickup": 68
            },
            {
                "id": 169,
                "x": 40.97,
                "y": 56.2,
                "r": "(-,f20')",
                "e": 223,
                "s": 30,
                "l": 343,
                "pickup": 69
            },
            {
                "id": 170,
                "x": 22.9,
                "y": 40.04,
                "r": "(-,f20')",
                "e": 380,
                "s": 30,
                "l": 500,
                "pickup": 70
            },
            {
                "id": 171,
                "x": 11.29,
                "y": 26.45,
                "r": "(-,e20')",
                "e": 281,
                "s": 30,
                "l": 401,
                "pickup": 71
            },
            {
                "id": 172,
                "x": 28.72,
                "y": 39.93,
                "r": "(-,e20')",
                "e": 416,
                "s": 30,
                "l": 536,
                "pickup": 72
            },
            {
                "id": 173,
                "x": 10.38,
                "y": 19.7,
                "r": "(-,e20')",
                "e": 396,
                "s": 30,
                "l": 516,
                "pickup": 73
            },
            {
                "id": 174,
                "x": 17.3,
                "y": 37.0,
                "r": "(-,e20')",
                "e": 365,
                "s": 30,
                "l": 485,
                "pickup": 74
            },
            {
                "id": 175,
                "x": 24.11,
                "y": 44.47,
                "r": "(-,e20')",
                "e": 374,
                "s": 30,
                "l": 494,
                "pickup": 75
            },
            {
                "id": 176,
                "x": 3.2,
                "y": 13.23,
                "r": "(-,e20')",
                "e": 435,
                "s": 30,
                "l": 555,
                "pickup": 76
            },
            {
                "id": 177,
                "x": 33.92,
                "y": 25.62,
                "r": "(-,f20')",
                "e": 416,
                "s": 30,
                "l": 536,
                "pickup": 77
            },
            {
                "id": 178,
                "x": 38.25,
                "y": 34.17,
                "r": "(-,f20')",
                "e": 341,
                "s": 30,
                "l": 461,
                "pickup": 78
            },
            {
                "id": 179,
                "x": 23.73,
                "y": 42.22,
                "r": "(-,e20')",
                "e": 342,
                "s": 30,
                "l": 462,
                "pickup": 79
            },
            {
                "id": 180,
                "x": 47.96,
                "y": 52.22,
                "r": "(-,f20')",
                "e": 330,
                "s": 30,
                "l": 450,
                "pickup": 80
            },
            {
                "id": 181,
                "x": 59.83,
                "y": 9.46,
                "r": "(-,e20')",
                "e": 235,
                "s": 30,
                "l": 355,
                "pickup": 81
            },
            {
                "id": 182,
                "x": 33.78,
                "y": 48.11,
                "r": "(-,f20')",
                "e": 393,
                "s": 30,
                "l": 513,
                "pickup": 82
            },
            {
                "id": 183,
                "x": 23.8,
                "y": 10.07,
                "r": "(-,f20')",
                "e": 343,
                "s": 30,
                "l": 463,
                "pickup": 83
            },
            {
                "id": 184,
                "x": 40.14,
                "y": 8.57,
                "r": "(-,e20')",
                "e": 422,
                "s": 30,
                "l": 542,
                "pickup": 84
            },
            {
                "id": 185,
                "x": 16.56,
                "y": 22.42,
                "r": "(-,e20')",
                "e": 324,
                "s": 30,
                "l": 444,
                "pickup": 85
            },
            {
                "id": 186,
                "x": 38.53,
                "y": 43.64,
                "r": "(-,e20')",
                "e": 287,
                "s": 30,
                "l": 407,
                "pickup": 86
            },
            {
                "id": 187,
                "x": 50.35,
                "y": 32.89,
                "r": "(-,f20')",
                "e": 285,
                "s": 30,
                "l": 405,
                "pickup": 87
            },
            {
                "id": 188,
                "x": 20.32,
                "y": 47.7,
                "r": "(-,e20')",
                "e": 357,
                "s": 30,
                "l": 477,
                "pickup": 88
            },
            {
                "id": 189,
                "x": 19.32,
                "y": 51.81,
                "r": "(-,e20')",
                "e": 396,
                "s": 30,
                "l": 516,
                "pickup": 89
            },
            {
                "id": 190,
                "x": 37.51,
                "y": 25.22,
                "r": "(-,f20')",
                "e": 414,
                "s": 30,
                "l": 534,
                "pickup": 90
            },
            {
                "id": 191,
                "x": 38.01,
                "y": 43.89,
                "r": "(-,e20')",
                "e": 205,
                "s": 30,
                "l": 325,
                "pickup": 91
            },
            {
                "id": 192,
                "x": 29.36,
                "y": 30.19,
                "r": "(-,f20')",
                "e": 281,
                "s": 30,
                "l": 401,
                "pickup": 92
            },
            {
                "id": 193,
                "x": 40.29,
                "y": 52.16,
                "r": "(-,e20')",
                "e": 375,
                "s": 30,
                "l": 495,
                "pickup": 93
            },
            {
                "id": 194,
                "x": 8.54,
                "y": 40.73,
                "r": "(-,e20')",
                "e": 412,
                "s": 30,
                "l": 532,
                "pickup": 94
            },
            {
                "id": 195,
                "x": 10.68,
                "y": 18.18,
                "r": "(-,f20')",
                "e": 299,
                "s": 30,
                "l": 419,
                "pickup": 95
            },
            {
                "id": 196,
                "x": 39.57,
                "y": 17.27,
                "r": "(-,e20')",
                "e": 422,
                "s": 30,
                "l": 542,
                "pickup": 96
            },
            {
                "id": 197,
                "x": 18.96,
                "y": 8.97,
                "r": "(-,e20')",
                "e": 361,
                "s": 30,
                "l": 481,
                "pickup": 97
            },
            {
                "id": 198,
                "x": 1.22,
                "y": 26.7,
                "r": "(-,e20')",
                "e": 400,
                "s": 30,
                "l": 520,
                "pickup": 98
            },
            {
                "id": 199,
                "x": 14.79,
                "y": 6.49,
                "r": "(-,f20')",
                "e": 421,
                "s": 30,
                "l": 541,
                "pickup": 99
            },
            {
                "id": 200,
                "x": 11.94,
                "y": 39.17,
                "r": "(-,e20')",
                "e": 270,
                "s": 30,
                "l": 390,
                "pickup": 100
            }
        ]
    },
    "fleet": [
        {
            "truck_type": "heavy-duty truck (20' dry containers x2)",
            "trucks_available": 100,
            "fixed_cost": 74,
            "routing_cost": 0.8,
            "transitions": [
                [
                    0,
                    1,
                    "start"
                ],
                [
                    1,
                    2,
                    "(+,e20')"
                ],
                [
                    2,
                    3,
                    "(+,e20')"
                ],
                [
                    3,
                    2,
                    "(-,e20')"
                ],
                [
                    2,
                    1,
                    "(-,e20')"
                ],
                [
                    1,
                    4,
                    "(+,f20')"
                ],
                [
                    4,
                    1,
                    "(-,f20')"
                ],
                [
                    1,
                    5,
                    "end"
                ]
            ]
        }
    ]
}