{
    "name": "RC2-F2-W3-100",
    "nodes": {
        "depot": [
            {
                "id": 0,
                "x": 6.59,
                "y": 25.22,
                "r": "start",
                "e": 0,
                "s": 0,
                "l": 600
            },
            {
                "id": 201,
                "x": 6.59,
                "y": 25.22,
                "r": "end",
                "e": 0,
                "s": 0,
                "l": 600
            }
        ],
        "pickup": [
            {
                "id": 1,
                "x": 28.52,
                "y": 48.23,
                "r": "(+,f20')",
                "e": 343,
                "s": 30,
                "l": 403,
                "delivery": 101
            },
            {
                "id": 2,
                "x": 34.87,
                "y": 42.4,
                "r": "(+,f20')",
                "e": 54,
                "s": 30,
                "l": 114,
                "delivery": 102
            },
            {
                "id": 3,
                "x": 25.39,
                "y": 45.0,
                "r": "(+,e20')",
                "e": 68,
                "s": 30,
                "l": 188,
                "delivery": 103
            },
            {
                "id": 4,
                "x": 27.84,
                "y": 43.53,
                "r": "(+,e20')",
                "e": 196,
                "s": 30,
                "l": 256,
                "delivery": 104
            },
            {
                "id": 5,
                "x": 30.38,
                "y": 48.6,
                "r": "(+,f20')",
                "e": 233,
                "s": 30,
                "l": 293,
                "delivery": 105
            },
            {
                "id": 6,
                "x": 30.38,
                "y": 41.77,
                "r": "(+,e20')",
                "e": 202,
                "s": 30,
                "l": 262,
                "delivery": 106
            },
            {
                "id": 7,
                "x": 44.59,
                "y": 4.05,
                "r": "(+,f20')",
                "e": 332,
                "s": 30,
                "l": 452,
                "delivery": 107
            },
            {
                "id": 8,
                "x": 45.14,
                "y": 2.1,
                "r": "(+,e20')",
                "e": 279,
                "s": 30,
                "l": 399,
                "delivery": 108
            },
            {
                "id": 9,
                "x": 49.11,
                "y": 8.97,
                "r": "(+,e20')",
                "e": 232,
                "s": 30,
                "l": 352,
                "delivery": 109
            },
            {
                "id": 10,
                "x": 44.49,
                "y": 10.07,
                "r": "(+,f20')",
                "e": 169,
                "s": 30,
                "l": 229,
                "delivery": 110
            },
            {
                "id": 11,
                "x": 47.12,
                "y": 1.83,
                "r": "(+,f20')",
                "e": 295,
                "s": 30,
                "l": 355,
                "delivery": 111
            },
            {
                "id": 12,
                "x": 49.96,
                "y": 3.87,
                "r": "(+,e20')",
                "e": 224,
                "s": 30,
                "l": 344,
                "delivery": 112
            },
            {
                "id": 13,
                "x": 14.9,
                "y": 5.12,
                "r": "(+,e20')",
                "e": 211,
                "s": 30,
                "l": 331,
                "delivery": 113
            },
            {
                "id": 14,
                "x": 8.33,
                "y": 5.76,
                "r": "(+,f20')",
                "e": 223,
                "s": 30,
                "l": 283,
                "delivery": 114
            },
            {
                "id": 15,
                "x": 9.17,
                "y": 10.6,
                "r": "(+,f20')",
                "e": 327,
                "s": 30,
                "l": 447,
                "delivery": 115
            },
            {
                "id": 16,
                "x": 13.32,
                "y": 3.41,
                "r": "(+,f20')",
                "e": 340,
                "s": 30,
                "l": 460,
                "delivery": 116
            },
            {
                "id": 17,
                "x": 7.88,
                "y": 9.17,
                "r": "(+,f20')",
                "e": 303,
                "s": 30,
                "l": 363,
                "delivery": 117
            },
            {
                "id": 18,
                "x": 8.69,
                "y": 3.24,
                "r": "(+,e20')",
                "e": 290,
                "s": 30,
                "l": 350,
                "delivery": 118
            },
            {
                "id": 19,
                "x": 3.41,
                "y": 30.35,
                "r": "(+,e20')",
                "e": 48,
                "s": 30,
                "l": 108,
                "delivery": 119
            },
            {
                "id": 20,
                "x": 1.79,
                "y": 36.62,
                "r": "(+,f20')",
                "e": 229,
                "s": 30,
                "l": 349,
                "delivery": 120
            },
            {
                "id": 21,
                "x": 11.42,
                "y": 31.98,
                "r": "(+,e20')",
                "e": 177,
                "s": 30,
                "l": 237,
                "delivery": 121
            },
            {
                "id": 22,
                "x": 9.81,
                "y": 30.26,
                "r": "(+,f20')",
                "e": 300,
                "s": 30,
                "l": 420,
                "delivery": 122
            },
            {
                "id": 23,
                "x": 7.75,
                "y": 29.17,
                "r": "(+,e20')",
                "e": 38,
                "s": 30,
                "l": 98,
                "delivery": 123
            },
            {
                "id": 24,
                "x": 3.57,
                "y": 34.31,
                "r": "(+,e20')",
                "e": 390,
                "s": 30,
                "l": 510,
                "delivery": 124
            },
            {
                "id": 25,
                "x": 3.24,
                "y": 38.5,
                "r": "(+,f20')",
                "e": 291,
                "s": 30,
                "l": 411,
                "delivery": 125
            },
            {
                "id": 26,
                "x": 55.48,
                "y": 29.79,
                "r": "(+,e20')",
                "e": 61,
                "s": 30,
                "l": 181,
                "delivery": 126
            },
            {
                "id": 27,
                "x": 51.81,
                "y": 31.84,
                "r": "(+,f20')",
                "e": 73,
                "s": 30,
                "l": 133,
                "delivery": 127
            },
            {
                "id": 28,
                "x": 59.08,
                "y": 32.67,
                "r": "(+,f20')",
                "e": 313,
                "s": 30,
                "l": 433,
                "delivery": 128
            },
            {
                "id": 29,
                "x": 52.33,
                "y": 37.44,
                "r": "(+,e20')",
                "e": 178,
                "s": 30,
                "l": 238,
                "delivery": 129
            },
            {
                "id": 30,
                "x": 56.57,
                "y": 32.12,
                "r": "(+,f20')",
                "e": 165,
                "s": 30,
                "l": 285,
                "delivery": 130
            },
            {
                "id": 31,
                "x": 53.54,
                "y": 31.62,
                "r": "(+,e20')",
                "e": 76,
                "s": 30,
                "l": 196,
                "delivery": 131
            },
            {
                "id": 32,
                "x": 51.44,
                "y": 34.97,
                "r": "(+,e20')",
                "e": 329,
                "s": 30,
                "l": 389,
                "delivery": 132
            },
            {
                "id": 33,
                "x": 25.86,
                "y": 16.39,
                "r": "(+,e20')",
                "e": 47,
                "s": 30,
                "l": 167,
                "delivery": 133
            },
            {
                "id": 34,
                "x": 30.2,
                "y": 15.6,
                "r": "(+,f20')",
                "e": 73,
                "s": 30,
                "l": 193,
                "delivery": 134
            },
            {
                "id": 35,
                "x": 33.76,
                "y": 18.2,
                "r": "(+,f20')",
                "e": 142,
                "s": 30,
                "l": 262,
                "delivery": 135
            },
            {
                "id": 36,
                "x": 26.35,
                "y": 19.13,
                "r": "(+,f20')",
                "e": 186,
                "s": 30,
                "l": 246,
                "delivery": 136
            },
            {
                "id": 37,
                "x": 25.88,
                "y": 20.45,
                "r": "(+,e20')",
                "e": 186,
                "s": 30,
                "l": 246,
                "delivery": 137
            },
            {
                "id": 38,
                "x": 27.93,
                "y": 25.55,
                "r": "(+,e20')",
                "e": 41,
                "s": 30,
                "l": 101,
                "delivery": 138
            },
            {
                "id": 39,
                "x": 28.12,
                "y": 16.16,
                "r": "(+,f20')",
                "e": 38,
                "s": 30,
                "l": 98,
                "delivery": 139
            },
            {
                "id": 40,
                "x": 48.17,
                "y": 17.12,
                "r": "(+,e20')",
                "e": 345,
                "s": 30,
                "l": 405,
                "delivery": 140
            },
            {
                "id": 41,
                "x": 49.97,
                "y": 17.23,
                "r": "(+,f20')",
                "e": 54,
                "s": 30,
                "l": 174,
                "delivery": 141
            },
            {
                "id": 42,
                "x": 31.57,
                "y": 32.01,
                "r": "(+,f20')",
                "e": 176,
                "s": 30,
                "l": 296,
                "delivery": 142
            },
            {
                "id": 43,
                "x": 34.61,
                "y": 57.56,
                "r": "(+,f20')",
                "e": 146,
                "s": 30,
                "l": 266,
                "delivery": 143
            },
            {
                "id": 44,
                "x": 27.4,
                "y": 55.82,
                "r": "(+,f20')",
                "e": 69,
                "s": 30,
                "l": 189,
                "delivery": 144
            },
            {
                "id": 45,
                "x": 5.19,
                "y": 46.11,
                "r": "(+,e20')",
                "e": 114,
                "s": 30,
                "l": 174,
                "delivery": 145
            },
            {
                "id": 46,
                "x": 58.63,
                "y": 45.26,
                "r": "(+,e20')",
                "e": 107,
                "s": 30,
                "l": 227,
                "delivery": 146
            },
            {
                "id": 47,
                "x": 29.61,
                "y": 33.66,
                "r": "(+,f20')",
                "e": 105,
                "s": 30,
                "l": 165,
                "delivery": 147
            },
            {
                "id": 48,
                "x": 22.97,
                "y": 11.34,
                "r": "(+,e20')",
                "e": 256,
                "s": 30,
                "l": 316,
                "delivery": 148
            },
            {
                "id": 49,
                "x": 18.08,
                "y": 49.78,
                "r": "(+,e20')",
                "e": 247,
                "s": 30,
                "l": 307,
                "delivery": 149
            },
            {
                "id": 50,
                "x": 3.69,
                "y": 59.09,
                "r": "(+,e20')",
                "e": 46,
                "s": 30,
                "l": 166,
                "delivery": 150
            },
            {
                "id": 51,
                "x": 43.5,
                "y": 22.17,
                "r": "(+,e20')",
                "e": 271,
                "s": 30,
                "l": 331,
                "delivery": 151
            },
            {
                "id": 52,
                "x": 39.59,
                "y": 26.23,
                "r": "(+,f20')",
                "e": 280,
                "s": 30,
                "l": 340,
                "delivery": 152
            },
            {
                "id": 53,
                "x": 56.53,
                "y": 50.8,
                "r": "(+,f20')",
                "e": 155,
                "s": 30,
                "l": 275,
                "delivery": 153
            },
            {
                "id": 54,
                "x": 24.52,
                "y": 33.68,
                "r": "(+,f20')",
                "e": 75,
                "s": 30,
                "l": 135,
                "delivery": 154
            },
            {
                "id": 55,
                "x": 47.19,
                "y": 44.02,
                "r": "(+,e20')",
                "e": 92,
                "s": 30,
                "l": 152,
                "delivery": 155
            },
            {
                "id": 56,
                "x": 16.25,
                "y": 50.91,
                "r": "(+,f20')",
                "e": 135,
                "s": 30,
                "l": 195,
                "delivery": 156
            },
            {
                "id": 57,
                "x": 18.09,
                "y": 44.44,
                "r": "(+,f20')",
                "e": 194,
                "s": 30,
                "l": 254,
                "delivery": 157
            },
            {
                "id": 58,
                "x": 24.51,
                "y": 9.86,
                "r": "(+,e20')",
                "e": 320,
                "s": 30,
                "l": 380,
                "delivery": 158
            },
            {
                "id": 59,
                "x": 27.38,
                "y": 1.37,
                "r": "(+,f20')",
                "e": 112,
                "s": 30,
                "l": 172,
                "delivery": 159
            },
            {
                "id": 60,
                "x": 54.89,
                "y": 23.98,
                "r": "(+,e20')",
                "e": 259,
                "s": 30,
                "l": 379,
                "delivery": 160
            },
            {
                "id": 61,
                "x": 14.64,
                "y": 18.89,
                "r": "(+,f20')",
                "e": 263,
                "s": 30,
                "l": 323,
                "delivery": 161
            },
            {
                "id": 62,
                "x": 46.25,
                "y": 53.96,
                "r": "(+,e20')",
                "e": 237,
                "s": 30,
                "l": 357,
                "delivery": 162
            },
            {
                "id": 63,
                "x": 46.44,
                "y": 56.86,
                "r": "(+,e20')",
                "e": 198,
                "s": 30,
                "l": 258,
                "delivery": 163
            },
            {
                "id": 64,
                "x": 28.49,
                "y": 8.02,
                "r": "(+,f20')",
                "e": 263,
                "s": 30,
                "l": 383,
                "delivery": 164
            },
            {
                "id": 65,
                "x": 41.09,
                "y": 18.42,
                "r": "(+,e20')",
                "e": 284,
                "s": 30,
                "l": 344,
                "delivery": 165
            },
            {
                "id": 66,
                "x": 11.42,
                "y": 53.03,
                "r": "(+,e20')",
                "e": 364,
                "s": 30,
                "l": 424,
                "delivery": 166
            },
            {
                "id": 67,
                "x": 29.3,
                "y": 6.97,
                "r": "(+,f20')",
                "e": 233,
                "s": 30,
                "l": 293,
                "delivery": 167
            },
            {
                "id": 68,
                "x": 18.78,
                "y": 43.97,
                "r": "(+,f20')",
                "e": 62,
                "s": 30,
                "l": 182,
                "delivery": 168
            },
            {
                "id": 69,
                "x": 36.52,
                "y": 29.08,
                "r": "(+,e20')",
                "e": 366,
                "s": 30,
                "l": 426,
                "delivery": 169
            },
            {
                "id": 70,
                "x": 15.6,
                "y": 48.54,
                "r": "(+,f20')",
                "e": 62,
                "s": 30,
                "l": 122,
                "delivery": 170
            },
            {
                "id": 71,
                "x": 45.01,
                "y": 50.27,
                "r": "(+,e20')",
                "e": 158,
                "s": 30,
                "l": 278,
                "delivery": 171
            },
            {
                "id": 72,
                "x": 19.71,
                "y": 0.64,
                "r": "(+,f20')",
                "e": 77,
                "s": 30,
                "l": 197,
                "delivery": 172
            },
            {
                "id": 73,
                "x": 22.89,
                "y": 3.02,
                "r": "(+,e20')",
                "e": 106,
                "s": 30,
                "l": 166,
                "delivery": 173
            },
            {
                "id": 74,
                "x": 48.26,
                "y": 44.64,
                "r": "(+,f20')",
                "e": 128,
                "s": 30,
                "l": 188,
                "delivery": 174
            },
            {
                "id": 75,
                "x": 41.72,
                "y": 34.73,
                "r": "(+,e20')",
                "e": 249,
                "s": 30,
                "l": 309,
                "delivery": 175
            },
            {
                "id": 76,
                "x": 2.82,
                "y": 55.4,
                "r": "(+,f20')",
                "e": 57,
                "s": 30,
                "l": 177,
                "delivery": 176
            },
            {
                "id": 77,
                "x": 43.09,
                "y": 24.39,
                "r": "(+,e20')",
                "e": 127,
                "s": 30,
                "l": 187,
                "delivery": 177
            },
            {
                "id": 78,
                "x": 54.05,
                "y": 58.22,
                "r": "(+,e20')",
                "e": 276,
                "s": 30,
                "l": 336,
                "delivery": 178
            },
            {
                "id": 79,
                "x": 13.38,
                "y": 49.95,
                "r": "(+,e20')",
                "e": 173,
                "s": 30,
                "l": 233,
                "delivery": 179
            },
            {
                "id": 80,
                "x": 0.16,
                "y": 51.43,
                "r": "(+,f20')",
                "e": 237,
                "s": 30,
                "l": 297,
                "delivery": 180
            },
            {
                "id": 81,
                "x": 26.55,
                "y": 57.21,
                "r": "(+,f20')",
                "e": 42,
                "s": 30,
                "l": 162,
                "delivery": 181
            },
            {
                "id": 82,
                "x": 55.2,
                "y": 16.26,
                "r": "(+,f20')",
                "e": 304,
                "s": 30,
                "l": 424,
                "delivery": 182
            },
            {
                "id": 83,
                "x": 4.96,
                "y": 48.82,
                "r": "(+,f20')",
                "e": 145,
                "s": 30,
                "l": 265,
                "delivery": 183
            },
            {
                "id": 84,
                "x": 38.58,
                "y": 57.86,
                "r": "(+,f20')",
                "e": 92,
                "s": 30,
                "l": 212,
                "delivery": 184
            },
            {
                "id": 85,
                "x": 41.68,
                "y": 18.67,
                "r": "(+,f20')",
                "e": 218,
                "s": 30,
                "l": 278,
                "delivery": 185
            },
            {
                "id": 86,
                "x": 38.57,
                "y": 37.72,
                "r": "(+,f20')",
                "e": 56,
                "s": 30,
                "l": 176,
                "delivery": 186
            },
            {
                "id": 87,
                "x": 40.76,
                "y": 26.67,
                "r": "(+,e20')",
                "e": 350,
                "s": 30,
                "l": 410,
                "delivery": 187
            },
            {
                "id": 88,
                "x": 4.39,
                "y": 55.82,
                "r": "(+,e20')",
                "e": 53,
                "s": 30,
                "l": 113,
                "delivery": 188
            },
            {
                "id": 89,
                "x": 32.52,
                "y": 5.59,
                "r": "(+,f20')",
                "e": 148,
                "s": 30,
                "l": 268,
                "delivery": 189
            },
            {
                "id": 90,
                "x": 23.35,
                "y": 3.2,
                "r": "(+,e20')",
                "e": 267,
                "s": 30,
                "l": 327,
                "delivery": 190
            },
            {
                "id": 91,
                "x": 58.2,
                "y": 21.48,
                "r": "(+,e20')",
                "e": 210,
                "s": 30,
                "l": 330,
                "delivery": 191
            },
            {
                "id": 92,
                "x": 52.88,
                "y": 23.74,
                "r": "(+,e20')",
                "e": 81,
                "s": 30,
                "l": 141,
                "delivery": 192
            },
            {
                "id": 93,
                "x": 7.94,
                "y": 60.0,
                "r": "(+,e20')",
                "e": 138,
                "s": 30,
                "l": 258,
                "delivery": 193
            },
            {
                "id": 94,
                "x": 49.0,
                "y": 57.89,
                "r": "(+,f20')",
                "e": 94,
                "s": 30,
                "l": 154,
                "delivery": 194
            },
            {
                "id": 95,
                "x": 4.07,
                "y": 54.52,
                "r": "(+,f20')",
                "e": 211,
                "s": 30,
                "l": 331,
                "delivery": 195
            },
            {
                "id": 96,
                "x": 20.27,
                "y": 34.6,
                "r": "(+,f20')",
                "e": 309,
                "s": 30,
                "l": 429,
                "delivery": 196
            },
            {
                "id": 97,
                "x": 46.49,
                "y": 44.35,
                "r": "(+,e20')",
                "e": 205,
                "s": 30,
                "l": 265,
                "delivery": 197
            },
            {
                "id": 98,
                "x": 3.72,
                "y": 50.93,
                "r": "(+,e20')",
                "e": 114,
                "s": 30,
                "l": 234,
                "delivery": 198
            },
            {
                "id": 99,
                "x": 6.25,
                "y": 49.17,
                "r": "(+,e20')",
                "e": 63,
                "s": 30,
                "l": 183,
                "delivery": 199
            },
            {
                "id": 100,
                "x": 53.46,
                "y": 53.32,
                "r": "(+,e20')",
                "e": 144,
                "s": 30,
                "l": 204,
                "delivery": 200
            }
        ],
        "delivery": [
            {
                "id": 101,
                "x": 33.61,
                "y": 45.0,
                "r": "(-,f20')",
                "e": 390,
                "s": 30,
                "l": 510,
                "pickup": 1
            },
            {
                "id": 102,
                "x": 32.33,
                "y": 41.63,
                "r": "(-,f20')",
                "e": 98,
                "s": 30,
                "l": 158,
                "pickup": 2
            },
            {
                "id": 103,
                "x": 32.73,
                "y": 49.05,
                "r": "(-,e20')",
                "e": 242,
                "s": 30,
                "l": 302,
                "pickup": 3
            },
            {
                "id": 104,
                "x": 27.73,
                "y": 46.53,
                "r": "(-,e20')",
                "e": 362,
                "s": 30,
                "l": 482,
                "pickup": 4
            },
            {
                "id": 105,
                "x": 33.11,
                "y": 46.57,
                "r": "(-,f20')",
                "e": 323,
                "s": 30,
                "l": 443,
                "pickup": 5
            },
            {
                "id": 106,
                "x": 27.82,
                "y": 40.55,
                "r": "(-,e20')",
                "e": 263,
                "s": 30,
                "l": 383,
                "pickup": 6
            },
            {
                "id": 107,
                "x": 43.76,
                "y": 5.51,
                "r": "(-,f20')",
                "e": 388,
                "s": 30,
                "l": 508,
                "pickup": 7
            },
            {
                "id": 108,
                "x": 50.58,
                "y": 5.51,
                "r": "(-,e20')",
                "e": 381,
                "s": 30,
                "l": 501,
                "pickup": 8
            },
            {
                "id": 109,
                "x": 50.16,
                "y": 7.27,
                "r": "(-,e20')",
                "e": 389,
                "s": 30,
                "l": 509,
                "pickup": 9
            },
            {
                "id": 110,
                "x": 47.12,
                "y": 10.64,
                "r": "(-,f20')",
                "e": 319,
                "s": 30,
                "l": 439,
                "pickup": 10
            },
            {
                "id": 111,
                "x": 44.55,
                "y": 7.0,
                "r": "(-,f20')",
                "e": 368,
                "s": 30,
                "l": 488,
                "pickup": 11
            },
            {
                "id": 112,
                "x": 49.65,
                "y": 1.13,
                "r": "(-,e20')",
                "e": 434,
                "s": 30,
                "l": 494,
                "pickup": 12
            },
            {
                "id": 113,
                "x": 7.44,
                "y": 7.34,
                "r": "(-,e20')",
                "e": 306,
                "s": 30,
                "l": 426,
                "pickup": 13
            },
            {
                "id": 114,
                "x": 13.46,
                "y": 11.5,
                "r": "(-,f20')",
                "e": 274,
                "s": 30,
                "l": 394,
                "pickup": 14
            },
            {
                "id": 115,
                "x": 15.69,
                "y": 10.02,
                "r": "(-,f20')",
                "e": 415,
                "s": 30,
                "l": 535,
                "pickup": 15
            },
            {
                "id": 116,
                "x": 11.06,
                "y": 2.74,
                "r": "(-,f20')",
                "e": 407,
                "s": 30,
                "l": 527,
                "pickup": 16
            },
            {
                "id": 117,
                "x": 14.59,
                "y": 7.34,
                "r": "(-,f20')",
                "e": 408,
                "s": 30,
                "l": 468,
                "pickup": 17
            },
            {
                "id": 118,
                "x": 11.06,
                "y": 10.25,
                "r": "(-,e20')",
                "e": 359,
                "s": 30,
                "l": 479,
                "pickup": 18
            },
            {
                "id": 119,
                "x": 3.03,
                "y": 32.61,
                "r": "(-,e20')",
                "e": 312,
                "s": 30,
                "l": 372,
                "pickup": 19
            },
            {
                "id": 120,
                "x": 8.85,
                "y": 37.16,
                "r": "(-,f20')",
                "e": 405,
                "s": 30,
                "l": 525,
                "pickup": 20
            },
            {
                "id": 121,
                "x": 7.62,
                "y": 38.87,
                "r": "(-,e20')",
                "e": 254,
                "s": 30,
                "l": 374,
                "pickup": 21
            },
            {
                "id": 122,
                "x": 5.52,
                "y": 29.68,
                "r": "(-,f20')",
                "e": 395,
                "s": 30,
                "l": 515,
                "pickup": 22
            },
            {
                "id": 123,
                "x": 10.56,
                "y": 36.23,
                "r": "(-,e20')",
                "e": 346,
                "s": 30,
                "l": 406,
                "pickup": 23
            },
            {
                "id": 124,
                "x": 5.87,
                "y": 37.42,
                "r": "(-,e20')",
                "e": 424,
                "s": 30,
                "l": 544,
                "pickup": 24
            },
            {
                "id": 125,
                "x": 11.56,
                "y": 34.31,
                "r": "(-,f20')",
                "e": 398,
                "s": 30,
                "l": 518,
                "pickup": 25
            },
            {
                "id": 126,
                "x": 53.12,
                "y": 40.16,
                "r": "(-,e20')",
                "e": 228,
                "s": 30,
                "l": 288,
                "pickup": 26
            },
            {
                "id": 127,
                "x": 56.11,
                "y": 37.23,
                "r": "(-,f20')",
                "e": 202,
                "s": 30,
                "l": 262,
                "pickup": 27
            },
            {
                "id": 128,
                "x": 49.48,
                "y": 32.64,
                "r": "(-,f20')",
                "e": 378,
                "s": 30,
                "l": 498,
                "pickup": 28
            },
            {
                "id": 129,
                "x": 58.99,
                "y": 34.97,
                "r": "(-,e20')",
                "e": 254,
                "s": 30,
                "l": 314,
                "pickup": 29
            },
            {
                "id": 130,
                "x": 55.33,
                "y": 39.46,
                "r": "(-,f20')",
                "e": 451,
                "s": 30,
                "l": 511,
                "pickup": 30
            },
            {
                "id": 131,
                "x": 59.0,
                "y": 37.23,
                "r": "(-,e20')",
                "e": 209,
                "s": 30,
                "l": 329,
                "pickup": 31
            },
            {
                "id": 132,
                "x": 51.59,
                "y": 36.27,
                "r": "(-,e20')",
                "e": 455,
                "s": 30,
                "l": 515,
                "pickup": 32
            },
            {
                "id": 133,
                "x": 25.75,
                "y": 24.65,
                "r": "(-,e20')",
                "e": 209,
                "s": 30,
                "l": 269,
                "pickup": 33
            },
            {
                "id": 134,
                "x": 32.79,
                "y": 22.23,
                "r": "(-,f20')",
                "e": 137,
                "s": 30,
                "l": 257,
                "pickup": 34
            },
            {
                "id": 135,
                "x": 31.68,
                "y": 17.2,
                "r": "(-,f20')",
                "e": 310,
                "s": 30,
                "l": 370,
                "pickup": 35
            },
            {
                "id": 136,
                "x": 33.39,
                "y": 20.45,
                "r": "(-,f20')",
                "e": 263,
                "s": 30,
                "l": 383,
                "pickup": 36
            },
            {
                "id": 137,
                "x": 26.18,
                "y": 21.85,
                "r": "(-,e20')",
                "e": 263,
                "s": 30,
                "l": 383,
                "pickup": 37
            },
            {
                "id": 138,
                "x": 32.33,
                "y": 24.51,
                "r": "(-,e20')",
                "e": 308,
                "s": 30,
                "l": 368,
                "pickup": 38
            },
            {
                "id": 139,
                "x": 30.09,
                "y": 24.8,
                "r": "(-,f20')",
                "e": 272,
                "s": 30,
                "l": 392,
                "pickup": 39
            },
            {
                "id": 140,
                "x": 23.43,
                "y": 32.41,
                "r": "(-,e20')",
                "e": 480,
                "s": 30,
                "l": 540,
                "pickup": 40
            },
            {
                "id": 141,
                "x": 41.77,
                "y": 46.68,
                "r": "(-,f20')",
                "e": 406,
                "s": 30,
                "l": 526,
                "pickup": 41
            },
            {
                "id": 142,
                "x": 18.94,
                "y": 49.02,
                "r": "(-,f20')",
                "e": 316,
                "s": 30,
                "l": 376,
                "pickup": 42
            },
            {
                "id": 143,
                "x": 41.7,
                "y": 20.8,
                "r": "(-,f20')",
                "e": 455,
                "s": 30,
                "l": 515,
                "pickup": 43
            },
            {
                "id": 144,
                "x": 35.05,
                "y": 3.55,
                "r": "(-,f20')",
                "e": 423,
                "s": 30,
                "l": 483,
                "pickup": 44
            },
            {
                "id": 145,
                "x": 5.41,
                "y": 50.61,
                "r": "(-,e20')",
                "e": 273,
                "s": 30,
                "l": 393,
                "pickup": 45
            },
            {
                "id": 146,
                "x": 41.42,
                "y": 37.11,
                "r": "(-,e20')",
                "e": 306,
                "s": 30,
                "l": 426,
                "pickup": 46
            },
            {
                "id": 147,
                "x": 3.92,
                "y": 52.12,
                "r": "(-,f20')",
                "e": 468,
                "s": 30,
                "l": 528,
                "pickup": 47
            },
            {
                "id": 148,
                "x": 59.9,
                "y": 58.23,
                "r": "(-,e20')",
                "e": 369,
                "s": 30,
                "l": 429,
                "pickup": 48
            },
            {
                "id": 149,
                "x": 57.19,
                "y": 18.92,
                "r": "(-,e20')",
                "e": 395,
                "s": 30,
                "l": 515,
                "pickup": 49
            },
            {
                "id": 150,
                "x": 57.0,
                "y": 52.04,
                "r": "(-,e20')",
                "e": 256,
                "s": 30,
                "l": 376,
                "pickup": 50
            },
            {
                "id": 151,
                "x": 53.49,
                "y": 16.13,
                "r": "(-,e20')",
                "e": 362,
                "s": 30,
                "l": 422,
                "pickup": 51
            },
            {
                "id": 152,
                "x": 8.3,
                "y": 57.27,
                "r": "(-,f20')",
                "e": 455,
                "s": 30,
                "l": 515,
                "pickup": 52
            },
            {
                "id": 153,
                "x": 51.16,
                "y": 16.37,
                "r": "(-,f20')",
                "e": 232,
                "s": 30,
                "l": 352,
                "pickup": 53
            },
            {
                "id": 154,
                "x": 17.99,
                "y": 43.4,
                "r": "(-,f20')",
                "e": 479,
                "s": 30,
                "l": 539,
                "pickup": 54
            },
            {
                "id": 155,
                "x": 34.3,
                "y": 7.65,
                "r": "(-,e20')",
                "e": 202,
                "s": 30,
                "l": 322,
                "pickup": 55
            },
            {
                "id": 156,
                "x": 3.85,
                "y": 16.67,
                "r": "(-,f20')",
                "e": 265,
                "s": 30,
                "l": 325,
                "pickup": 56
            },
            {
                "id": 157,
                "x": 55.58,
                "y": 13.08,
                "r": "(-,f20')",
                "e": 343,
                "s": 30,
                "l": 463,
                "pickup": 57
            },
            {
                "id": 158,
                "x": 56.69,
                "y": 22.12,
                "r": "(-,e20')",
                "e": 391,
                "s": 30,
                "l": 511,
                "pickup": 58
            },
            {
                "id": 159,
                "x": 17.69,
                "y": 54.54,
                "r": "(-,f20')",
                "e": 213,
                "s": 30,
                "l": 333,
                "pickup": 59
            },
            {
                "id": 160,
                "x": 59.29,
                "y": 8.17,
                "r": "(-,e20')",
                "e": 380,
                "s": 30,
                "l": 500,
                "pickup": 60
            },
            {
                "id": 161,
                "x": 44.66,
                "y": 57.21,
                "r": "(-,f20')",
                "e": 355,
                "s": 30,
                "l": 475,
                "pickup": 61
            },
            {
                "id": 162,
                "x": 24.81,
                "y": 5.85,
                "r": "(-,e20')",
                "e": 358,
                "s": 30,
                "l": 478,
                "pickup": 62
            },
            {
                "id": 163,
                "x": 18.88,
                "y": 14.93,
                "r": "(-,e20')",
                "e": 425,
                "s": 30,
                "l": 545,
                "pickup": 63
            },
            {
                "id": 164,
                "x": 47.22,
                "y": 26.36,
                "r": "(-,f20')",
                "e": 416,
                "s": 30,
                "l": 476,
                "pickup": 64
            },
            {
                "id": 165,
                "x": 10.23,
                "y": 58.94,
                "r": "(-,e20')",
                "e": 370,
                "s": 30,
                "l": 490,
                "pickup": 65
            },
            {
                "id": 166,
                "x": 30.14,
                "y": 33.07,
                "r": "(-,e20')",
                "e": 424,
                "s": 30,
                "l": 544,
                "pickup": 66
            },
            {
                "id": 167,
                "x": 49.57,
                "y": 19.59,
                "r": "(-,f20')",
                "e": 388,
                "s": 30,
                "l": 508,
                "pickup": 67
            },
            {
                "id": 168,
                "x": 47.39,
                "y": 48.25,
                "r": "(-,f20')",
                "e": 331,
                "s": 30,
                "l": 391,
                "pickup": 68
            },
            {
                "id": 169,
                "x": 33.89,
                "y": 30.95,
                "r": "(-,e20')",
                "e": 457,
                "s": 30,
                "l": 517,
                "pickup": 69
            },
            {
                "id": 170,
                "x": 42.52,
                "y": 15.77,
                "r": "(-,f20')",
                "e": 183,
                "s": 30,
                "l": 303,
                "pickup": 70
            },
            {
                "id": 171,
                "x": 33.5,
                "y": 0.94,
                "r": "(-,e20')",
                "e": 313,
                "s": 30,
                "l": 433,
                "pickup": 71
            },
            {
                "id": 172,
                "x": 48.03,
                "y": 56.45,
                "r": "(-,f20')",
                "e": 342,
                "s": 30,
                "l": 402,
                "pickup": 72
            },
            {
                "id": 173,
                "x": 18.03,
                "y": 37.87,
                "r": "(-,e20')",
                "e": 279,
                "s": 30,
                "l": 339,
                "pickup": 73
            },
            {
                "id": 174,
                "x": 25.6,
                "y": 32.9,
                "r": "(-,f20')",
                "e": 347,
                "s": 30,
                "l": 467,
                "pickup": 74
            },
            {
                "id": 175,
                "x": 0.64,
                "y": 59.78,
                "r": "(-,e20')",
                "e": 373,
                "s": 30,
                "l": 493,
                "pickup": 75
            },
            {
                "id": 176,
                "x": 1.97,
                "y": 51.57,
                "r": "(-,f20')",
                "e": 183,
                "s": 30,
                "l": 243,
                "pickup": 76
            },
            {
                "id": 177,
                "x": 41.68,
                "y": 34.48,
                "r": "(-,e20')",
                "e": 293,
                "s": 30,
                "l": 413,
                "pickup": 77
            },
            {
                "id": 178,
                "x": 12.38,
                "y": 56.62,
                "r": "(-,e20')",
                "e": 370,
                "s": 30,
                "l": 490,
                "pickup": 78
            },
            {
                "id": 179,
                "x": 39.89,
                "y": 29.49,
                "r": "(-,e20')",
                "e": 400,
                "s": 30,
                "l": 460,
                "pickup": 79
            },
            {
                "id": 180,
                "x": 54.23,
                "y": 20.51,
                "r": "(-,f20')",
                "e": 454,
                "s": 30,
                "l": 514,
                "pickup": 80
            },
            {
                "id": 181,
                "x": 54.69,
                "y": 17.64,
                "r": "(-,f20')",
                "e": 186,
                "s": 30,
                "l": 306,
                "pickup": 81
            },
            {
                "id": 182,
                "x": 17.15,
                "y": 27.01,
                "r": "(-,f20')",
                "e": 385,
                "s": 30,
                "l": 505,
                "pickup": 82
            },
            {
                "id": 183,
                "x": 34.51,
                "y": 4.2,
                "r": "(-,f20')",
                "e": 433,
                "s": 30,
                "l": 493,
                "pickup": 83
            },
            {
                "id": 184,
                "x": 21.64,
                "y": 0.09,
                "r": "(-,f20')",
                "e": 364,
                "s": 30,
                "l": 484,
                "pickup": 84
            },
            {
                "id": 185,
                "x": 50.41,
                "y": 50.62,
                "r": "(-,f20')",
                "e": 294,
                "s": 30,
                "l": 414,
                "pickup": 85
            },
            {
                "id": 186,
                "x": 41.79,
                "y": 20.68,
                "r": "(-,f20')",
                "e": 235,
                "s": 30,
                "l": 295,
                "pickup": 86
            },
            {
                "id": 187,
                "x": 53.11,
                "y": 16.96,
                "r": "(-,e20')",
                "e": 400,
                "s": 30,
                "l": 520,
                "pickup": 87
            },
            {
                "id": 188,
                "x": 32.4,
                "y": 10.03,
                "r": "(-,e20')",
                "e": 478,
                "s": 30,
                "l": 538,
                "pickup": 88
            },
            {
                "id": 189,
                "x": 9.19,
                "y": 55.13,
                "r": "(-,f20')",
                "e": 302,
                "s": 30,
                "l": 422,
                "pickup": 89
            },
            {
                "id": 190,
                "x": 5.65,
                "y": 57.57,
                "r": "(-,e20')",
                "e": 397,
                "s": 30,
                "l": 517,
                "pickup": 90
            },
            {
                "id": 191,
                "x": 54.12,
                "y": 20.19,
                "r": "(-,e20')",
                "e": 434,
                "s": 30,
                "l": 494,
                "pickup": 91
            },
            {
                "id": 192,
                "x": 52.42,
                "y": 58.91,
                "r": "(-,e20')",
                "e": 246,
                "s": 30,
                "l": 366,
                "pickup": 92
            },
            {
                "id": 193,
                "x": 18.32,
                "y": 30.66,
                "r": "(-,e20')",
                "e": 307,
                "s": 30,
                "l": 427,
                "pickup": 93
            },
            {
                "id": 194,
                "x": 6.93,
                "y": 55.0,
                "r": "(-,f20')",
                "e": 336,
                "s": 30,
                "l": 456,
                "pickup": 94
            },
            {
                "id": 195,
                "x": 42.48,
                "y": 40.98,
                "r": "(-,f20')",
                "e": 384,
                "s": 30,
                "l": 504,
                "pickup": 95
            },
            {
                "id": 196,
                "x": 13.15,
                "y": 57.69,
                "r": "(-,f20')",
                "e": 475,
                "s": 30,
                "l": 535,
                "pickup": 96
            },
            {
                "id": 197,
                "x": 19.52,
                "y": 29.46,
                "r": "(-,e20')",
                "e": 376,
                "s": 30,
                "l": 496,
                "pickup": 97
            },
            {
                "id": 198,
                "x": 57.95,
                "y": 24.6,
                "r": "(-,e20')",
                "e": 358,
                "s": 30,
                "l": 478,
                "pickup": 98
            },
            {
                "id": 199,
                "x": 53.47,
                "y": 53.69,
                "r": "(-,e20')",
                "e": 299,
                "s": 30,
                "l": 419,
                "pickup": 99
            },
            {
                "id": 200,
                "x": 29.58,
                "y": 57.23,
                "r": "(-,e20')",
                "e": 265,
                "s": 30,
                "l": 385,
                "pickup": 100
            }
        ]
    },
    "fleet": [
        {
            "truck_type": "heavy-duty truck (20' dry containers x2)",
            "trucks_available": 100,
            "fixed_cost": 74,
            "routing_cost": 0.8,
            "transitions": [
                [
                    0,
                    1,
                    "start"
                ],
                [
                    1,
                    2,
                    "(+,e20')"
                ],
                [
                    2,
                    3,
                    "(+,e20')"
                ],
                [
                    3,
                    2,
                    "(-,e20')"
                ],
                [
                    2,
                    1,
                    "(-,e20')"
                ],
                [
                    1,
                    4,
                    "(+,f20')"
                ],
                [
                    4,
                    1,
                    "(-,f20')"
                ],
                [
                    1,
                    5,
                    "end"
                ]
            ]
        }
    ]
}